README.rst
setup.py
ASTFormatter.egg-info/PKG-INFO
ASTFormatter.egg-info/SOURCES.txt
ASTFormatter.egg-info/dependency_links.txt
ASTFormatter.egg-info/top_level.txt
astformatter/__init__.py