Metadata-Version: 1.0
Name: ASTFormatter
Version: 0.6.2
Summary: The ASTFormatter class accepts an AST tree and returns a valid source code representation of that tree.
Home-page: https://github.com/darkfoxprime/python-astformatter
Author: Johnson Earls
Author-email: darkfoxprime@gmail.com
License: ISC
Keywords: AST,source code formatter
Platform: UNKNOWN
Classifier: Development Status :: 4 - Beta
Classifier: Intended Audience :: Developers
Classifier: Topic :: Software Development :: Libraries :: Python Modules
Classifier: License :: OSI Approved :: ISC License (ISCL)
Classifier: Programming Language :: Python :: 2.6
Classifier: Programming Language :: Python :: 2.7
Classifier: Programming Language :: Python :: 3.4
